{
  "locations": [
    { "name": "Carmichael Student Center", "coordinates": [-84.5831447839737, 34.038533480073355] },
    { "name": "Carmichael Student Center Entrance", "coordinates": [-84.58283364772798, 34.038660170620055] },
    { "name": "Academic Learning Center", "coordinates": [-84.58317697048189, 34.03931806936354] },
    { "name": "Academic Learning Center Entrance", "coordinates": [-84.58298921585084, 34.03978259614599] },
    { "name": "English Building", "coordinates": [-84.58414524793626, 34.03942475516541] },
    { "name": "English Building South", "coordinates": [-84.5841532945633, 34.03910025210137] },
    { "name": "English Building North", "coordinates": [-84.58402454853059, 34.03979815441523] },
    { "name": "University Hall", "coordinates": [-84.58437055349351, 34.038938000103784] },
    { "name": "Willingham Hall", "coordinates": [-84.58483189344408, 34.038973562212] },
    { "name": "Social Sciences", "coordinates": [-84.58521813154222, 34.03870240076022] },
    { "name": "Technology Services", "coordinates": [-84.58511178527453, 34.04324444304241] },
    { "name": "Jolley Lodge", "coordinates": [-84.58503997779815, 34.041975382594565] },
    { "name": "Bailey Performance Center", "coordinates": [-84.58388467029071, 34.04104538235975] },
    { "name": "Zuckerman Museum", "coordinates": [-84.58332319433181, 34.041127569948884] },
    { "name": "Prillaman Health Sciences", "coordinates": [-84.5823230947359, 34.04126007515278] },
    { "name": "Prillaman Health Sciences East", "coordinates": [-84.58227837728104, 34.04040804794117] },
    { "name": "Prillaman Health Sciences West", "coordinates": [-84.58162052602621, 34.04049249904415] },
    { "name": "Central Parking Deck", "coordinates": [-84.58155510939581, 34.04091628989932] },
    { "name": "Visual Arts", "coordinates": [-84.58495900426912, 34.04014013820758] },
    { "name": "Wilson Annex", "coordinates": [-84.58407716154898, 34.040382041842314] },
    { "name": "Wilson Building", "coordinates": [-84.5831444233547, 34.04021534710124] },
    { "name": "Music Building", "coordinates": [-84.58287930990906, 34.040181974276315] },
    { "name": "The Commons", "coordinates": [-84.5822049725835, 34.040112254887596] },
    { "name": "Burruss Building", "coordinates": [-84.58182548615811, 34.03916307618097] },
    { "name": "Burruss Building East", "coordinates": [-84.58151844214942, 34.039334634541554] },
    { "name": "Bagwell Education Building", "coordinates": [-84.58087532494412, 34.0396379119677] },
    { "name": "Bagwell Education Building South", "coordinates": [-84.5809418434928, 34.039037425081695] },
    { "name": "Kennesaw Hall", "coordinates": [-84.580944525696, 34.03889684364226] },
    { "name": "Kennesaw Hall East", "coordinates": [-84.5807963755791, 34.037958423913985] },
    { "name": "Kennesaw Hall South", "coordinates": [-84.58038669152127, 34.03813234820042] },
    { "name": "Convocation Center", "coordinates": [-84.5804216302843, 34.03739857647659] },
    { "name": "Siegel Student Recreation Center", "coordinates": [-84.58134592872163, 34.03685306796862] },
    { "name": "Siegel Student Recreation East", "coordinates": [-84.58239021303122, 34.03685051220012] },
    { "name": "Siegel Student Recreation North", "coordinates": [-84.58220111729591, 34.03752287232788] },
    { "name": "East Parking Deck", "coordinates": [-84.58115296368257, 34.0366216129326] },
    { "name": "University Bookstore", "coordinates": [-84.5831169079928, 34.03785497707045] },
    { "name": "Sturgis Library", "coordinates": [-84.58373969823, 34.03817439372666] },
    { "name": "Wilder Communications Center", "coordinates": [-84.52081934524365, 33.93455660617953] },
    { "name": "Civil Engineering Soils Lab", "coordinates": [-84.52036756689206, 33.93540362312106] }
  ]
}